{
  "project_info": {
    "project_number": "114370865255",
    "project_id": "fir-firebase-5ecdb",
    "storage_bucket": "fir-firebase-5ecdb.appspot.com"
  },
  "client": [
    {
      "client_info": {
        "mobilesdk_app_id": "1:114370865255:android:92754e4664591982330cc2",
        "android_client_info": {
          "package_name": "com.example.demo_firebase_project"
        }
      },
      "oauth_client": [
        {
          "client_id": "114370865255-vrf8sfn9mgumrqseohog8p031g71qhl7.apps.googleusercontent.com",
          "client_type": 1,
          "android_info": {
            "package_name": "com.example.demo_firebase_project",
            "certificate_hash": "c10c293ae200e3feb557c9bfbea9bde5eb5091af"
          }
        },
        {
          "client_id": "114370865255-bda0gl66o2fpsgk9j03igp7m50n0b9vh.apps.googleusercontent.com",
          "client_type": 3
        }
      ],
      "api_key": [
        {
          "current_key": "AIzaSyBH8FtizYeST6wU1J-u9e6PAOokTomueR8"
        }
      ],
      "services": {
        "appinvite_service": {
          "other_platform_oauth_client": [
            {
              "client_id": "114370865255-bda0gl66o2fpsgk9j03igp7m50n0b9vh.apps.googleusercontent.com",
              "client_type": 3
            }
          ]
        }
      }
    }
  ],
  "configuration_version": "1"
}